Workbook

Sheet Instrucciones
A1: Presupuesto anual de una UMA o zoológico
A2: Zoorigen · Club VIP · Versión 1.0 · 22 de octubre de 2026 · Material original de Zoorigen
B4: Para qué sirve
C5: Planea el año de tu unidad: alimentación, insumos, servicios, personal y mantenimiento, mes por mes. El libro suma los totales, calcula qué parte del presupuesto es cada concepto y, si capturas el gasto real, te muestra la diferencia y el porcentaje ejercido, con gráficas. Las cantidades del ejemplo son ILUSTRATIVAS: no son referencia de costos reales.
B7: Qué hay en cada hoja
B8: Presupuesto | C8: Tu plan: un renglón por concepto y una columna por mes.
B9: Real | C9: Lo que realmente gastaste, con la misma estructura.
B10: Resumen | C10: Totales por categoría, presupuesto contra real y gráficas.
B12: Cómo usarlo, paso a paso
B13: Paso 1 | C13: En «Resumen» escribe el año y la moneda.
B14: Paso 2 | C14: En «Presupuesto» borra los EJEMPLOS y escribe tus conceptos: elige la categoría de la lista, escribe el concepto y el monto de cada mes.
B15: Paso 3 | C15: El total anual y el porcentaje del total se calculan solos. Puedes agregar tantos conceptos como necesites en las filas vacías.
B16: Paso 4 | C16: Cada mes, captura lo gastado en «Real» (una fila por concepto, con su categoría).
B17: Paso 5 | C17: En «Resumen» revisa la diferencia por categoría: positiva significa que gastaste menos de lo presupuestado; negativa, que te pasaste.
B19: Colores y celdas
B20: Celdas blancas | C20: Son para que escribas o elijas de una lista.
B21: Celdas grises | C21: Se calculan solas con fórmulas: no las borres ni escribas encima.
B22: Filas de EJEMPLO | C22: Las filas marcadas con la palabra EJEMPLO (fondo dorado claro) solo muestran cómo se llena. Bórralas antes de empezar con tus datos reales: selecciona la fila y usa «Eliminar contenido» para conservar las fórmulas.
B24: Ten en cuenta
C25: Los montos son los que tú captures. El libro no trae precios ni referencias.
C26: Para presupuestos que debas presentar a una autoridad, a un patronato o a un financiador, usa el formato que ellos pidan: este libro es una herramienta de planeación.
B28: Aviso
C29: Material de apoyo de Zoorigen: no sustituye el criterio profesional ni la asesoría legal. Consulta siempre la normatividad vigente.

Sheet Presupuesto
A1: Presupuesto anual
A2: Zoorigen · Material de apoyo. Cifras de ejemplo ilustrativas: bórralas y captura las tuyas.
A4: Categoría | B4: Concepto | C4: Ene | D4: Feb | E4: Mar | F4: Abr | G4: May | H4: Jun | I4: Jul | J4: Ago | K4: Sep | L4: Oct | M4: Nov | N4: Dic | O4: Total anual | P4: % del total | Q4: Nota
A5: Alimentación | B5: Alimento (ejemplo) | C5: 18000 | D5: 18500 | E5: 19000 | F5: 18000 | G5: 18500 | H5: 19000 | I5: 18000 | J5: 18500 | K5: 19000 | L5: 18000 | M5: 18500 | N5: 19000 | O5: =IF(AND(A5="",B5=""),"",SUM(C5:N5)) | P5: =IF(OR(O5="",SUM($O$5:$O$104)=0),"",O5/SUM($O$5:$O$104)) | Q5: EJEMPLO
A6: Insumos y material | B6: Material de limpieza (ejemplo) | C6: 3500 | D6: 3900 | E6: 3500 | F6: 3900 | G6: 3500 | H6: 3900 | I6: 3500 | J6: 3900 | K6: 3500 | L6: 3900 | M6: 3500 | N6: 3900 | O6: =IF(AND(A6="",B6=""),"",SUM(C6:N6)) | P6: =IF(OR(O6="",SUM($O$5:$O$104)=0),"",O6/SUM($O$5:$O$104)) | Q6: EJEMPLO
A7: Servicios | B7: Agua y luz (ejemplo) | C7: 6200 | D7: 6200 | E7: 6200 | F7: 6200 | G7: 6200 | H7: 6200 | I7: 6200 | J7: 6200 | K7: 6200 | L7: 6200 | M7: 6200 | N7: 6200 | O7: =IF(AND(A7="",B7=""),"",SUM(C7:N7)) | P7: =IF(OR(O7="",SUM($O$5:$O$104)=0),"",O7/SUM($O$5:$O$104)) | Q7: EJEMPLO
A8: Personal | B8: Nómina y honorarios (ejemplo) | C8: 42000 | D8: 42000 | E8: 42000 | F8: 42000 | G8: 42000 | H8: 42000 | I8: 42000 | J8: 42000 | K8: 42000 | L8: 42000 | M8: 42000 | N8: 42000 | O8: =IF(AND(A8="",B8=""),"",SUM(C8:N8)) | P8: =IF(OR(O8="",SUM($O$5:$O$104)=0),"",O8/SUM($O$5:$O$104)) | Q8: EJEMPLO
A9: Mantenimiento e infraestructura | B9: Reparaciones (ejemplo) | C9: 15000 | D9: 2500 | E9: 2500 | F9: 2500 | G9: 15000 | H9: 2500 | I9: 2500 | J9: 2500 | K9: 15000 | L9: 2500 | M9: 2500 | N9: 2500 | O9: =IF(AND(A9="",B9=""),"",SUM(C9:N9)) | P9: =IF(OR(O9="",SUM($O$5:$O$104)=0),"",O9/SUM($O$5:$O$104)) | Q9: EJEMPLO
O10: =IF(AND(A10="",B10=""),"",SUM(C10:N10)) | P10: =IF(OR(O10="",SUM($O$5:$O$104)=0),"",O10/SUM($O$5:$O$104))
O11: =IF(AND(A11="",B11=""),"",SUM(C11:N11)) | P11: =IF(OR(O11="",SUM($O$5:$O$104)=0),"",O11/SUM($O$5:$O$104))
O12: =IF(AND(A12="",B12=""),"",SUM(C12:N12)) | P12: =IF(OR(O12="",SUM($O$5:$O$104)=0),"",O12/SUM($O$5:$O$104))
O13: =IF(AND(A13="",B13=""),"",SUM(C13:N13)) | P13: =IF(OR(O13="",SUM($O$5:$O$104)=0),"",O13/SUM($O$5:$O$104))
O14: =IF(AND(A14="",B14=""),"",SUM(C14:N14)) | P14: =IF(OR(O14="",SUM($O$5:$O$104)=0),"",O14/SUM($O$5:$O$104))
O15: =IF(AND(A15="",B15=""),"",SUM(C15:N15)) | P15: =IF(OR(O15="",SUM($O$5:$O$104)=0),"",O15/SUM($O$5:$O$104))
O16: =IF(AND(A16="",B16=""),"",SUM(C16:N16)) | P16: =IF(OR(O16="",SUM($O$5:$O$104)=0),"",O16/SUM($O$5:$O$104))
O17: =IF(AND(A17="",B17=""),"",SUM(C17:N17)) | P17: =IF(OR(O17="",SUM($O$5:$O$104)=0),"",O17/SUM($O$5:$O$104))
O18: =IF(AND(A18="",B18=""),"",SUM(C18:N18)) | P18: =IF(OR(O18="",SUM($O$5:$O$104)=0),"",O18/SUM($O$5:$O$104))
O19: =IF(AND(A19="",B19=""),"",SUM(C19:N19)) | P19: =IF(OR(O19="",SUM($O$5:$O$104)=0),"",O19/SUM($O$5:$O$104))
O20: =IF(AND(A20="",B20=""),"",SUM(C20:N20)) | P20: =IF(OR(O20="",SUM($O$5:$O$104)=0),"",O20/SUM($O$5:$O$104))
O21: =IF(AND(A21="",B21=""),"",SUM(C21:N21)) | P21: =IF(OR(O21="",SUM($O$5:$O$104)=0),"",O21/SUM($O$5:$O$104))
... O104: =IF(AND(A104="",B104=""),"",SUM(C104:N104)) | P104: =IF(OR(O104="",SUM($O$5:$O$104)=0),"",O104/SUM($O$5:$O$104))
B106: Total | C106: =SUM(C5:C104) | D106: =SUM(D5:D104) | E106: =SUM(E5:E104) | F106: =SUM(F5:F104) | G106: =SUM(G5:G104) | H106: =SUM(H5:H104) | I106: =SUM(I5:I104) | J106: =SUM(J5:J104) | ... O106: =SUM(O5:O104)

Sheet Real
A1: Gasto real
A2: Zoorigen · Material de apoyo. Captura lo realmente gastado, por concepto y por mes.
A4: Categoría | B4: Concepto | C4: Ene | D4: Feb | E4: Mar | F4: Abr | G4: May | H4: Jun | I4: Jul | J4: Ago | K4: Sep | L4: Oct | M4: Nov | N4: Dic | O4: Total anual | P4: Nota
A5: Alimentación | B5: Alimento (ejemplo) | C5: 18900 | D5: 17900 | E5: 19000 | F5: 18000 | G5: 18500 | H5: 19000 | I5: 18000 | J5: 18500 | K5: 19000 | L5: 18000 | M5: 18500 | N5: 19000 | O5: =IF(AND(A5="",B5=""),"",SUM(C5:N5)) | P5: EJEMPLO
A6: Insumos y material | B6: Material de limpieza (ejemplo) | C6: 4400 | D6: 3300 | E6: 3500 | F6: 3900 | G6: 3500 | H6: 3900 | I6: 3500 | J6: 3900 | K6: 3500 | L6: 3900 | M6: 3500 | N6: 3900 | O6: =IF(AND(A6="",B6=""),"",SUM(C6:N6)) | P6: EJEMPLO
A7: Servicios | B7: Agua y luz (ejemplo) | C7: 7100 | D7: 5600 | E7: 6200 | F7: 6200 | G7: 6200 | H7: 6200 | I7: 6200 | J7: 6200 | K7: 6200 | L7: 6200 | M7: 6200 | N7: 6200 | O7: =IF(AND(A7="",B7=""),"",SUM(C7:N7)) | P7: EJEMPLO
A8: Personal | B8: Nómina y honorarios (ejemplo) | C8: 42900 | D8: 41400 | E8: 42000 | F8: 42000 | G8: 42000 | H8: 42000 | I8: 42000 | J8: 42000 | K8: 42000 | L8: 42000 | M8: 42000 | N8: 42000 | O8: =IF(AND(A8="",B8=""),"",SUM(C8:N8)) | P8: EJEMPLO
A9: Mantenimiento e infraestructura | B9: Reparaciones (ejemplo) | C9: 15900 | D9: 1900 | E9: 2500 | F9: 2500 | G9: 15000 | H9: 2500 | I9: 2500 | J9: 2500 | K9: 15000 | L9: 2500 | M9: 2500 | N9: 2500 | O9: =IF(AND(A9="",B9=""),"",SUM(C9:N9)) | P9: EJEMPLO
O10: =IF(AND(A10="",B10=""),"",SUM(C10:N10))
O11: =IF(AND(A11="",B11=""),"",SUM(C11:N11))
O12: =IF(AND(A12="",B12=""),"",SUM(C12:N12))
O13: =IF(AND(A13="",B13=""),"",SUM(C13:N13))
O14: =IF(AND(A14="",B14=""),"",SUM(C14:N14))
O15: =IF(AND(A15="",B15=""),"",SUM(C15:N15))
O16: =IF(AND(A16="",B16=""),"",SUM(C16:N16))
O17: =IF(AND(A17="",B17=""),"",SUM(C17:N17))
O18: =IF(AND(A18="",B18=""),"",SUM(C18:N18))
O19: =IF(AND(A19="",B19=""),"",SUM(C19:N19))
O20: =IF(AND(A20="",B20=""),"",SUM(C20:N20))
O21: =IF(AND(A21="",B21=""),"",SUM(C21:N21))
... O104: =IF(AND(A104="",B104=""),"",SUM(C104:N104))
B106: Total | C106: =SUM(C5:C104) | D106: =SUM(D5:D104) | E106: =SUM(E5:E104) | F106: =SUM(F5:F104) | G106: =SUM(G5:G104) | H106: =SUM(H5:H104) | I106: =SUM(I5:I104) | J106: =SUM(J5:J104) | ... O106: =SUM(O5:O104)

Sheet Resumen
A1: Resumen del presupuesto
A2: Presupuesto contra gasto real por categoría.
A3: Año | B3: 2027 | C3: Moneda | D3: MXN
A5: Categoría | B5: Presupuestado | C5: Gasto real | D5: Diferencia | E5: % ejercido
A6: Alimentación | B6: =SUMIF(Presupuesto!$A$5:$A$104,$A6,Presupuesto!$O$5:$O$104) | C6: =SUMIF(Real!$A$5:$A$104,$A6,Real!$O$5:$O$104) | D6: =B6-C6 | E6: =IF(B6=0,"",C6/B6)
A7: Insumos y material | B7: =SUMIF(Presupuesto!$A$5:$A$104,$A7,Presupuesto!$O$5:$O$104) | C7: =SUMIF(Real!$A$5:$A$104,$A7,Real!$O$5:$O$104) | D7: =B7-C7 | E7: =IF(B7=0,"",C7/B7)
A8: Servicios | B8: =SUMIF(Presupuesto!$A$5:$A$104,$A8,Presupuesto!$O$5:$O$104) | C8: =SUMIF(Real!$A$5:$A$104,$A8,Real!$O$5:$O$104) | D8: =B8-C8 | E8: =IF(B8=0,"",C8/B8)
A9: Personal | B9: =SUMIF(Presupuesto!$A$5:$A$104,$A9,Presupuesto!$O$5:$O$104) | C9: =SUMIF(Real!$A$5:$A$104,$A9,Real!$O$5:$O$104) | D9: =B9-C9 | E9: =IF(B9=0,"",C9/B9)
A10: Mantenimiento e infraestructura | B10: =SUMIF(Presupuesto!$A$5:$A$104,$A10,Presupuesto!$O$5:$O$104) | C10: =SUMIF(Real!$A$5:$A$104,$A10,Real!$O$5:$O$104) | D10: =B10-C10 | E10: =IF(B10=0,"",C10/B10)
A11: Otros | B11: =SUMIF(Presupuesto!$A$5:$A$104,$A11,Presupuesto!$O$5:$O$104) | C11: =SUMIF(Real!$A$5:$A$104,$A11,Real!$O$5:$O$104) | D11: =B11-C11 | E11: =IF(B11=0,"",C11/B11)
A12: Total | B12: =SUM(B6:B11) | C12: =SUM(C6:C11) | D12: =SUM(D6:D11) | E12: =IF(B12=0,"",C12/B12)
A15: Por mes
A16: Mes | B16: Presupuestado | C16: Gasto real
A17: Ene | B17: =SUM(Presupuesto!C$5:C$104) | C17: =SUM(Real!C$5:C$104)
A18: Feb | B18: =SUM(Presupuesto!D$5:D$104) | C18: =SUM(Real!D$5:D$104)
A19: Mar | B19: =SUM(Presupuesto!E$5:E$104) | C19: =SUM(Real!E$5:E$104)
A20: Abr | B20: =SUM(Presupuesto!F$5:F$104) | C20: =SUM(Real!F$5:F$104)
A21: May | B21: =SUM(Presupuesto!G$5:G$104) | C21: =SUM(Real!G$5:G$104)
A22: Jun | B22: =SUM(Presupuesto!H$5:H$104) | C22: =SUM(Real!H$5:H$104)
A23: Jul | B23: =SUM(Presupuesto!I$5:I$104) | C23: =SUM(Real!I$5:I$104)
A24: Ago | B24: =SUM(Presupuesto!J$5:J$104) | C24: =SUM(Real!J$5:J$104)
A25: Sep | B25: =SUM(Presupuesto!K$5:K$104) | C25: =SUM(Real!K$5:K$104)
A26: Oct | B26: =SUM(Presupuesto!L$5:L$104) | C26: =SUM(Real!L$5:L$104)
A27: Nov | B27: =SUM(Presupuesto!M$5:M$104) | C27: =SUM(Real!M$5:M$104)
A28: Dic | B28: =SUM(Presupuesto!N$5:N$104) | C28: =SUM(Real!N$5:N$104)
