Workbook

Sheet Instrucciones
A1: Registro de ingresos, bajas y traslados de ejemplares
A2: Zoorigen · Club VIP · Versión 1.0 · 22 de octubre de 2026 · Material original de Zoorigen
B4: Para qué sirve
C5: Lleva el movimiento de los ejemplares de tu UMA, PIMVS, zoológico o centro: quién ingresa, quién causa baja y quién se traslada, con su documento de respaldo. La hoja «Resumen» te da por especie la existencia al inicio del año, los ingresos, las bajas, los traslados y la existencia al cierre. Es un registro interno de apoyo: NO sustituye los informes, bitácoras ni formatos que la autoridad te solicite.
B7: Qué hay en cada hoja
B8: Ejemplares | C8: La lista de ejemplares con su especie, sexo y marca o identificación.
B9: Movimientos | C9: Un renglón por cada ingreso, baja o traslado, con el documento que lo respalda.
B10: Resumen | C10: Cuenta por especie para el año que elijas.
B12: Cómo usarlo, paso a paso
B13: Paso 1 | C13: En «Ejemplares» borra los EJEMPLOS y escribe tus ejemplares con un identificador único. Escribe la especie de forma consistente: el resumen agrupa por el nombre común tal como lo escribas.
B14: Paso 2 | C14: En «Movimientos» elige el ejemplar, la fecha, el tipo (Ingreso, Baja, Traslado saliente o Traslado entrante) y el motivo. Anota el documento que respalda el movimiento (por ejemplo, el número o la descripción del oficio, factura o nota de remisión) y el origen o destino.
B15: Paso 3 | C15: La columna «Efecto» suma 1 cuando entra un ejemplar y resta 1 cuando sale. La especie y el año se calculan solos.
B16: Paso 4 | C16: En «Resumen» escribe el año y, en la columna A, cada especie como aparece en «Ejemplares». Se calcula la existencia al inicio, los movimientos del año y la existencia al cierre.
B17: Paso 5 | C17: Revisa la columna «Revisión»: te avisa si el cierre calculado no coincide con la suma de todos los movimientos.
B19: Colores y celdas
B20: Celdas blancas | C20: Son para que escribas o elijas de una lista.
B21: Celdas grises | C21: Se calculan solas con fórmulas: no las borres ni escribas encima.
B22: Filas de EJEMPLO | C22: Las filas marcadas con la palabra EJEMPLO (fondo dorado claro) solo muestran cómo se llena. Bórralas antes de empezar con tus datos reales: selecciona la fila y usa «Eliminar contenido» para conservar las fórmulas.
B24: Ten en cuenta
C25: Los documentos que deben acompañar cada movimiento (por ejemplo los de legal procedencia o de traslado) los define la normatividad vigente: consulta la norma y a tu asesor legal. Aquí solo hay un campo de texto para anotarlos.
C26: Si un ejemplar nace en la unidad, regístralo como Ingreso con el motivo «Nacimiento».
B28: Aviso
C29: Material de apoyo de Zoorigen: no sustituye el criterio profesional ni la asesoría legal. Consulta siempre la normatividad vigente.

Sheet Ejemplares
A1: Ejemplares
A2: Zoorigen · Material de apoyo (registro interno, no oficial)
A4: Identificador | B4: Nombre común (especie) | C4: Nombre científico | D4: Sexo | E4: Marca o identificación | F4: Observaciones | G4: Nota
A5: EJ-001 | B5: Especie de ejemplo A | C5: (nombre científico) | D5: Hembra | E5: Marca 0001 | G5: EJEMPLO
A6: EJ-002 | B6: Especie de ejemplo A | C6: (nombre científico) | D6: Macho | E6: Marca 0002 | G6: EJEMPLO
A7: EJ-003 | B7: Especie de ejemplo B | C7: (nombre científico) | D7: Indeterminado | E7: Marca 0003 | G7: EJEMPLO
A8: EJ-004 | B8: Especie de ejemplo B | C8: (nombre científico) | D8: Hembra | E8: Marca 0004 | G8: EJEMPLO
A9: EJ-005 | B9: Especie de ejemplo C | C9: (nombre científico) | D9: Macho | E9: Marca 0005 | G9: EJEMPLO

Sheet Movimientos
A1: Movimientos de ejemplares
A2: Zoorigen · Material de apoyo. Anota el documento que respalda cada movimiento.
A4: Fecha | B4: Ejemplar | C4: Especie | D4: Tipo | E4: Motivo | F4: Documento que lo respalda | G4: Origen o destino | H4: Responsable | I4: Efecto | J4: Año | K4: Observaciones | L4: Nota
A5: 45726 | B5: EJ-001 | C5: =IF(B5="","",IFERROR(INDEX(Ejemplares!$B$5:$B$304,MATCH(B5,Ejemplares!$A$5:$A$304,0)),"Ejemplar no encontrado")) | D5: Ingreso | E5: Adquisición | F5: Descripción del documento (ejemplo) | G5: Origen de ejemplo | H5: Nombre | I5: =IF(D5="","",IF(OR(D5="Ingreso",D5="Traslado entrante"),1,-1)) | J5: =IF(A5="","",YEAR(A5)) | L5: EJEMPLO
A6: 45726 | B6: EJ-002 | C6: =IF(B6="","",IFERROR(INDEX(Ejemplares!$B$5:$B$304,MATCH(B6,Ejemplares!$A$5:$A$304,0)),"Ejemplar no encontrado")) | D6: Ingreso | E6: Adquisición | F6: Descripción del documento (ejemplo) | G6: Origen de ejemplo | H6: Nombre | I6: =IF(D6="","",IF(OR(D6="Ingreso",D6="Traslado entrante"),1,-1)) | J6: =IF(A6="","",YEAR(A6)) | L6: EJEMPLO
A7: 46071 | B7: EJ-003 | C7: =IF(B7="","",IFERROR(INDEX(Ejemplares!$B$5:$B$304,MATCH(B7,Ejemplares!$A$5:$A$304,0)),"Ejemplar no encontrado")) | D7: Ingreso | E7: Nacimiento | F7: Acta interna de nacimiento (ejemplo) | G7: Nacido en la unidad | H7: Nombre | I7: =IF(D7="","",IF(OR(D7="Ingreso",D7="Traslado entrante"),1,-1)) | J7: =IF(A7="","",YEAR(A7)) | L7: EJEMPLO
A8: 46114 | B8: EJ-004 | C8: =IF(B8="","",IFERROR(INDEX(Ejemplares!$B$5:$B$304,MATCH(B8,Ejemplares!$A$5:$A$304,0)),"Ejemplar no encontrado")) | D8: Traslado entrante | E8: Intercambio o préstamo | F8: Descripción del documento (ejemplo) | G8: Otra unidad (ejemplo) | H8: Nombre | I8: =IF(D8="","",IF(OR(D8="Ingreso",D8="Traslado entrante"),1,-1)) | J8: =IF(A8="","",YEAR(A8)) | L8: EJEMPLO
A9: 46193 | B9: EJ-005 | C9: =IF(B9="","",IFERROR(INDEX(Ejemplares!$B$5:$B$304,MATCH(B9,Ejemplares!$A$5:$A$304,0)),"Ejemplar no encontrado")) | D9: Ingreso | E9: Rescate o entrega | F9: Descripción del documento (ejemplo) | G9: Entrega voluntaria (ejemplo) | H9: Nombre | I9: =IF(D9="","",IF(OR(D9="Ingreso",D9="Traslado entrante"),1,-1)) | J9: =IF(A9="","",YEAR(A9)) | L9: EJEMPLO
A10: 46242 | B10: EJ-002 | C10: =IF(B10="","",IFERROR(INDEX(Ejemplares!$B$5:$B$304,MATCH(B10,Ejemplares!$A$5:$A$304,0)),"Ejemplar no encontrado")) | D10: Baja | E10: Muerte | F10: Registro de mortalidad (ejemplo) | H10: Nombre | I10: =IF(D10="","",IF(OR(D10="Ingreso",D10="Traslado entrante"),1,-1)) | J10: =IF(A10="","",YEAR(A10)) | L10: EJEMPLO
A11: 46280 | B11: EJ-005 | C11: =IF(B11="","",IFERROR(INDEX(Ejemplares!$B$5:$B$304,MATCH(B11,Ejemplares!$A$5:$A$304,0)),"Ejemplar no encontrado")) | D11: Traslado saliente | E11: Liberación | F11: Descripción del documento (ejemplo) | G11: Destino de ejemplo | H11: Nombre | I11: =IF(D11="","",IF(OR(D11="Ingreso",D11="Traslado entrante"),1,-1)) | J11: =IF(A11="","",YEAR(A11)) | L11: EJEMPLO
C12: =IF(B12="","",IFERROR(INDEX(Ejemplares!$B$5:$B$304,MATCH(B12,Ejemplares!$A$5:$A$304,0)),"Ejemplar no encontrado")) | I12: =IF(D12="","",IF(OR(D12="Ingreso",D12="Traslado entrante"),1,-1)) | J12: =IF(A12="","",YEAR(A12))
C13: =IF(B13="","",IFERROR(INDEX(Ejemplares!$B$5:$B$304,MATCH(B13,Ejemplares!$A$5:$A$304,0)),"Ejemplar no encontrado")) | I13: =IF(D13="","",IF(OR(D13="Ingreso",D13="Traslado entrante"),1,-1)) | J13: =IF(A13="","",YEAR(A13))
C14: =IF(B14="","",IFERROR(INDEX(Ejemplares!$B$5:$B$304,MATCH(B14,Ejemplares!$A$5:$A$304,0)),"Ejemplar no encontrado")) | I14: =IF(D14="","",IF(OR(D14="Ingreso",D14="Traslado entrante"),1,-1)) | J14: =IF(A14="","",YEAR(A14))
C15: =IF(B15="","",IFERROR(INDEX(Ejemplares!$B$5:$B$304,MATCH(B15,Ejemplares!$A$5:$A$304,0)),"Ejemplar no encontrado")) | I15: =IF(D15="","",IF(OR(D15="Ingreso",D15="Traslado entrante"),1,-1)) | J15: =IF(A15="","",YEAR(A15))
C16: =IF(B16="","",IFERROR(INDEX(Ejemplares!$B$5:$B$304,MATCH(B16,Ejemplares!$A$5:$A$304,0)),"Ejemplar no encontrado")) | I16: =IF(D16="","",IF(OR(D16="Ingreso",D16="Traslado entrante"),1,-1)) | J16: =IF(A16="","",YEAR(A16))
C17: =IF(B17="","",IFERROR(INDEX(Ejemplares!$B$5:$B$304,MATCH(B17,Ejemplares!$A$5:$A$304,0)),"Ejemplar no encontrado")) | I17: =IF(D17="","",IF(OR(D17="Ingreso",D17="Traslado entrante"),1,-1)) | J17: =IF(A17="","",YEAR(A17))
C18: =IF(B18="","",IFERROR(INDEX(Ejemplares!$B$5:$B$304,MATCH(B18,Ejemplares!$A$5:$A$304,0)),"Ejemplar no encontrado")) | I18: =IF(D18="","",IF(OR(D18="Ingreso",D18="Traslado entrante"),1,-1)) | J18: =IF(A18="","",YEAR(A18))
C19: =IF(B19="","",IFERROR(INDEX(Ejemplares!$B$5:$B$304,MATCH(B19,Ejemplares!$A$5:$A$304,0)),"Ejemplar no encontrado")) | I19: =IF(D19="","",IF(OR(D19="Ingreso",D19="Traslado entrante"),1,-1)) | J19: =IF(A19="","",YEAR(A19))
C20: =IF(B20="","",IFERROR(INDEX(Ejemplares!$B$5:$B$304,MATCH(B20,Ejemplares!$A$5:$A$304,0)),"Ejemplar no encontrado")) | I20: =IF(D20="","",IF(OR(D20="Ingreso",D20="Traslado entrante"),1,-1)) | J20: =IF(A20="","",YEAR(A20))
C21: =IF(B21="","",IFERROR(INDEX(Ejemplares!$B$5:$B$304,MATCH(B21,Ejemplares!$A$5:$A$304,0)),"Ejemplar no encontrado")) | I21: =IF(D21="","",IF(OR(D21="Ingreso",D21="Traslado entrante"),1,-1)) | J21: =IF(A21="","",YEAR(A21))
C22: =IF(B22="","",IFERROR(INDEX(Ejemplares!$B$5:$B$304,MATCH(B22,Ejemplares!$A$5:$A$304,0)),"Ejemplar no encontrado")) | I22: =IF(D22="","",IF(OR(D22="Ingreso",D22="Traslado entrante"),1,-1)) | J22: =IF(A22="","",YEAR(A22))
C23: =IF(B23="","",IFERROR(INDEX(Ejemplares!$B$5:$B$304,MATCH(B23,Ejemplares!$A$5:$A$304,0)),"Ejemplar no encontrado")) | I23: =IF(D23="","",IF(OR(D23="Ingreso",D23="Traslado entrante"),1,-1)) | J23: =IF(A23="","",YEAR(A23))
... C604: =IF(B604="","",IFERROR(INDEX(Ejemplares!$B$5:$B$304,MATCH(B604,Ejemplares!$A$5:$A$304,0)),"Ejemplar no encontrado")) | I604: =IF(D604="","",IF(OR(D604="Ingreso",D604="Traslado entrante"),1,-1)) | J604: =IF(A604="","",YEAR(A604))

Sheet Resumen
A1: Resumen anual por especie
A2: Escribe el año y las especies (como aparecen en Ejemplares).
A3: Año del resumen | B3: 2026
A5: Especie | B5: Existencia al 1 de enero | C5: Ingresos | D5: Bajas | E5: Traslados salientes | F5: Existencia al 31 de dic. | G5: Existencia actual | H5: Revisión
A6: Especie de ejemplo A | B6: =IF($A6="","",SUMIFS(Movimientos!$I$5:$I$604,Movimientos!$C$5:$C$604,$A6,Movimientos!$A$5:$A$604,"<"&DATE($B$3,1,1))) | C6: =IF($A6="","",SUMIFS(Movimientos!$I$5:$I$604,Movimientos!$C$5:$C$604,$A6,Movimientos!$J$5:$J$604,$B$3,Movimientos!$I$5:$I$604,1)) | D6: =IF($A6="","",COUNTIFS(Movimientos!$C$5:$C$604,$A6,Movimientos!$J$5:$J$604,$B$3,Movimientos!$D$5:$D$604,"Baja")) | E6: =IF($A6="","",COUNTIFS(Movimientos!$C$5:$C$604,$A6,Movimientos!$J$5:$J$604,$B$3,Movimientos!$D$5:$D$604,"Traslado saliente")) | F6: =IF($A6="","",B6+C6-D6-E6) | G6: =IF($A6="","",SUMIFS(Movimientos!$I$5:$I$604,Movimientos!$C$5:$C$604,$A6)) | H6: =IF($A6="","",IF(F6=SUMIFS(Movimientos!$I$5:$I$604,Movimientos!$C$5:$C$604,$A6,Movimientos!$A$5:$A$604,"<"&DATE($B$3+1,1,1)),"Coincide","Revisa los movimientos"))
A7: Especie de ejemplo B | B7: =IF($A7="","",SUMIFS(Movimientos!$I$5:$I$604,Movimientos!$C$5:$C$604,$A7,Movimientos!$A$5:$A$604,"<"&DATE($B$3,1,1))) | C7: =IF($A7="","",SUMIFS(Movimientos!$I$5:$I$604,Movimientos!$C$5:$C$604,$A7,Movimientos!$J$5:$J$604,$B$3,Movimientos!$I$5:$I$604,1)) | D7: =IF($A7="","",COUNTIFS(Movimientos!$C$5:$C$604,$A7,Movimientos!$J$5:$J$604,$B$3,Movimientos!$D$5:$D$604,"Baja")) | E7: =IF($A7="","",COUNTIFS(Movimientos!$C$5:$C$604,$A7,Movimientos!$J$5:$J$604,$B$3,Movimientos!$D$5:$D$604,"Traslado saliente")) | F7: =IF($A7="","",B7+C7-D7-E7) | G7: =IF($A7="","",SUMIFS(Movimientos!$I$5:$I$604,Movimientos!$C$5:$C$604,$A7)) | H7: =IF($A7="","",IF(F7=SUMIFS(Movimientos!$I$5:$I$604,Movimientos!$C$5:$C$604,$A7,Movimientos!$A$5:$A$604,"<"&DATE($B$3+1,1,1)),"Coincide","Revisa los movimientos"))
A8: Especie de ejemplo C | B8: =IF($A8="","",SUMIFS(Movimientos!$I$5:$I$604,Movimientos!$C$5:$C$604,$A8,Movimientos!$A$5:$A$604,"<"&DATE($B$3,1,1))) | C8: =IF($A8="","",SUMIFS(Movimientos!$I$5:$I$604,Movimientos!$C$5:$C$604,$A8,Movimientos!$J$5:$J$604,$B$3,Movimientos!$I$5:$I$604,1)) | D8: =IF($A8="","",COUNTIFS(Movimientos!$C$5:$C$604,$A8,Movimientos!$J$5:$J$604,$B$3,Movimientos!$D$5:$D$604,"Baja")) | E8: =IF($A8="","",COUNTIFS(Movimientos!$C$5:$C$604,$A8,Movimientos!$J$5:$J$604,$B$3,Movimientos!$D$5:$D$604,"Traslado saliente")) | F8: =IF($A8="","",B8+C8-D8-E8) | G8: =IF($A8="","",SUMIFS(Movimientos!$I$5:$I$604,Movimientos!$C$5:$C$604,$A8)) | H8: =IF($A8="","",IF(F8=SUMIFS(Movimientos!$I$5:$I$604,Movimientos!$C$5:$C$604,$A8,Movimientos!$A$5:$A$604,"<"&DATE($B$3+1,1,1)),"Coincide","Revisa los movimientos"))
B9: =IF($A9="","",SUMIFS(Movimientos!$I$5:$I$604,Movimientos!$C$5:$C$604,$A9,Movimientos!$A$5:$A$604,"<"&DATE($B$3,1,1))) | C9: =IF($A9="","",SUMIFS(Movimientos!$I$5:$I$604,Movimientos!$C$5:$C$604,$A9,Movimientos!$J$5:$J$604,$B$3,Movimientos!$I$5:$I$604,1)) | D9: =IF($A9="","",COUNTIFS(Movimientos!$C$5:$C$604,$A9,Movimientos!$J$5:$J$604,$B$3,Movimientos!$D$5:$D$604,"Baja")) | E9: =IF($A9="","",COUNTIFS(Movimientos!$C$5:$C$604,$A9,Movimientos!$J$5:$J$604,$B$3,Movimientos!$D$5:$D$604,"Traslado saliente")) | F9: =IF($A9="","",B9+C9-D9-E9) | G9: =IF($A9="","",SUMIFS(Movimientos!$I$5:$I$604,Movimientos!$C$5:$C$604,$A9)) | H9: =IF($A9="","",IF(F9=SUMIFS(Movimientos!$I$5:$I$604,Movimientos!$C$5:$C$604,$A9,Movimientos!$A$5:$A$604,"<"&DATE($B$3+1,1,1)),"Coincide","Revisa los movimientos"))
B10: =IF($A10="","",SUMIFS(Movimientos!$I$5:$I$604,Movimientos!$C$5:$C$604,$A10,Movimientos!$A$5:$A$604,"<"&DATE($B$3,1,1))) | C10: =IF($A10="","",SUMIFS(Movimientos!$I$5:$I$604,Movimientos!$C$5:$C$604,$A10,Movimientos!$J$5:$J$604,$B$3,Movimientos!$I$5:$I$604,1)) | D10: =IF($A10="","",COUNTIFS(Movimientos!$C$5:$C$604,$A10,Movimientos!$J$5:$J$604,$B$3,Movimientos!$D$5:$D$604,"Baja")) | E10: =IF($A10="","",COUNTIFS(Movimientos!$C$5:$C$604,$A10,Movimientos!$J$5:$J$604,$B$3,Movimientos!$D$5:$D$604,"Traslado saliente")) | F10: =IF($A10="","",B10+C10-D10-E10) | G10: =IF($A10="","",SUMIFS(Movimientos!$I$5:$I$604,Movimientos!$C$5:$C$604,$A10)) | H10: =IF($A10="","",IF(F10=SUMIFS(Movimientos!$I$5:$I$604,Movimientos!$C$5:$C$604,$A10,Movimientos!$A$5:$A$604,"<"&DATE($B$3+1,1,1)),"Coincide","Revisa los movimientos"))
B11: =IF($A11="","",SUMIFS(Movimientos!$I$5:$I$604,Movimientos!$C$5:$C$604,$A11,Movimientos!$A$5:$A$604,"<"&DATE($B$3,1,1))) | C11: =IF($A11="","",SUMIFS(Movimientos!$I$5:$I$604,Movimientos!$C$5:$C$604,$A11,Movimientos!$J$5:$J$604,$B$3,Movimientos!$I$5:$I$604,1)) | D11: =IF($A11="","",COUNTIFS(Movimientos!$C$5:$C$604,$A11,Movimientos!$J$5:$J$604,$B$3,Movimientos!$D$5:$D$604,"Baja")) | E11: =IF($A11="","",COUNTIFS(Movimientos!$C$5:$C$604,$A11,Movimientos!$J$5:$J$604,$B$3,Movimientos!$D$5:$D$604,"Traslado saliente")) | F11: =IF($A11="","",B11+C11-D11-E11) | G11: =IF($A11="","",SUMIFS(Movimientos!$I$5:$I$604,Movimientos!$C$5:$C$604,$A11)) | H11: =IF($A11="","",IF(F11=SUMIFS(Movimientos!$I$5:$I$604,Movimientos!$C$5:$C$604,$A11,Movimientos!$A$5:$A$604,"<"&DATE($B$3+1,1,1)),"Coincide","Revisa los movimientos"))
B12: =IF($A12="","",SUMIFS(Movimientos!$I$5:$I$604,Movimientos!$C$5:$C$604,$A12,Movimientos!$A$5:$A$604,"<"&DATE($B$3,1,1))) | C12: =IF($A12="","",SUMIFS(Movimientos!$I$5:$I$604,Movimientos!$C$5:$C$604,$A12,Movimientos!$J$5:$J$604,$B$3,Movimientos!$I$5:$I$604,1)) | D12: =IF($A12="","",COUNTIFS(Movimientos!$C$5:$C$604,$A12,Movimientos!$J$5:$J$604,$B$3,Movimientos!$D$5:$D$604,"Baja")) | E12: =IF($A12="","",COUNTIFS(Movimientos!$C$5:$C$604,$A12,Movimientos!$J$5:$J$604,$B$3,Movimientos!$D$5:$D$604,"Traslado saliente")) | F12: =IF($A12="","",B12+C12-D12-E12) | G12: =IF($A12="","",SUMIFS(Movimientos!$I$5:$I$604,Movimientos!$C$5:$C$604,$A12)) | H12: =IF($A12="","",IF(F12=SUMIFS(Movimientos!$I$5:$I$604,Movimientos!$C$5:$C$604,$A12,Movimientos!$A$5:$A$604,"<"&DATE($B$3+1,1,1)),"Coincide","Revisa los movimientos"))
B13: =IF($A13="","",SUMIFS(Movimientos!$I$5:$I$604,Movimientos!$C$5:$C$604,$A13,Movimientos!$A$5:$A$604,"<"&DATE($B$3,1,1))) | C13: =IF($A13="","",SUMIFS(Movimientos!$I$5:$I$604,Movimientos!$C$5:$C$604,$A13,Movimientos!$J$5:$J$604,$B$3,Movimientos!$I$5:$I$604,1)) | D13: =IF($A13="","",COUNTIFS(Movimientos!$C$5:$C$604,$A13,Movimientos!$J$5:$J$604,$B$3,Movimientos!$D$5:$D$604,"Baja")) | E13: =IF($A13="","",COUNTIFS(Movimientos!$C$5:$C$604,$A13,Movimientos!$J$5:$J$604,$B$3,Movimientos!$D$5:$D$604,"Traslado saliente")) | F13: =IF($A13="","",B13+C13-D13-E13) | G13: =IF($A13="","",SUMIFS(Movimientos!$I$5:$I$604,Movimientos!$C$5:$C$604,$A13)) | H13: =IF($A13="","",IF(F13=SUMIFS(Movimientos!$I$5:$I$604,Movimientos!$C$5:$C$604,$A13,Movimientos!$A$5:$A$604,"<"&DATE($B$3+1,1,1)),"Coincide","Revisa los movimientos"))
B14: =IF($A14="","",SUMIFS(Movimientos!$I$5:$I$604,Movimientos!$C$5:$C$604,$A14,Movimientos!$A$5:$A$604,"<"&DATE($B$3,1,1))) | C14: =IF($A14="","",SUMIFS(Movimientos!$I$5:$I$604,Movimientos!$C$5:$C$604,$A14,Movimientos!$J$5:$J$604,$B$3,Movimientos!$I$5:$I$604,1)) | D14: =IF($A14="","",COUNTIFS(Movimientos!$C$5:$C$604,$A14,Movimientos!$J$5:$J$604,$B$3,Movimientos!$D$5:$D$604,"Baja")) | E14: =IF($A14="","",COUNTIFS(Movimientos!$C$5:$C$604,$A14,Movimientos!$J$5:$J$604,$B$3,Movimientos!$D$5:$D$604,"Traslado saliente")) | F14: =IF($A14="","",B14+C14-D14-E14) | G14: =IF($A14="","",SUMIFS(Movimientos!$I$5:$I$604,Movimientos!$C$5:$C$604,$A14)) | H14: =IF($A14="","",IF(F14=SUMIFS(Movimientos!$I$5:$I$604,Movimientos!$C$5:$C$604,$A14,Movimientos!$A$5:$A$604,"<"&DATE($B$3+1,1,1)),"Coincide","Revisa los movimientos"))
B15: =IF($A15="","",SUMIFS(Movimientos!$I$5:$I$604,Movimientos!$C$5:$C$604,$A15,Movimientos!$A$5:$A$604,"<"&DATE($B$3,1,1))) | C15: =IF($A15="","",SUMIFS(Movimientos!$I$5:$I$604,Movimientos!$C$5:$C$604,$A15,Movimientos!$J$5:$J$604,$B$3,Movimientos!$I$5:$I$604,1)) | D15: =IF($A15="","",COUNTIFS(Movimientos!$C$5:$C$604,$A15,Movimientos!$J$5:$J$604,$B$3,Movimientos!$D$5:$D$604,"Baja")) | E15: =IF($A15="","",COUNTIFS(Movimientos!$C$5:$C$604,$A15,Movimientos!$J$5:$J$604,$B$3,Movimientos!$D$5:$D$604,"Traslado saliente")) | F15: =IF($A15="","",B15+C15-D15-E15) | G15: =IF($A15="","",SUMIFS(Movimientos!$I$5:$I$604,Movimientos!$C$5:$C$604,$A15)) | H15: =IF($A15="","",IF(F15=SUMIFS(Movimientos!$I$5:$I$604,Movimientos!$C$5:$C$604,$A15,Movimientos!$A$5:$A$604,"<"&DATE($B$3+1,1,1)),"Coincide","Revisa los movimientos"))
B16: =IF($A16="","",SUMIFS(Movimientos!$I$5:$I$604,Movimientos!$C$5:$C$604,$A16,Movimientos!$A$5:$A$604,"<"&DATE($B$3,1,1))) | C16: =IF($A16="","",SUMIFS(Movimientos!$I$5:$I$604,Movimientos!$C$5:$C$604,$A16,Movimientos!$J$5:$J$604,$B$3,Movimientos!$I$5:$I$604,1)) | D16: =IF($A16="","",COUNTIFS(Movimientos!$C$5:$C$604,$A16,Movimientos!$J$5:$J$604,$B$3,Movimientos!$D$5:$D$604,"Baja")) | E16: =IF($A16="","",COUNTIFS(Movimientos!$C$5:$C$604,$A16,Movimientos!$J$5:$J$604,$B$3,Movimientos!$D$5:$D$604,"Traslado saliente")) | F16: =IF($A16="","",B16+C16-D16-E16) | G16: =IF($A16="","",SUMIFS(Movimientos!$I$5:$I$604,Movimientos!$C$5:$C$604,$A16)) | H16: =IF($A16="","",IF(F16=SUMIFS(Movimientos!$I$5:$I$604,Movimientos!$C$5:$C$604,$A16,Movimientos!$A$5:$A$604,"<"&DATE($B$3+1,1,1)),"Coincide","Revisa los movimientos"))
B17: =IF($A17="","",SUMIFS(Movimientos!$I$5:$I$604,Movimientos!$C$5:$C$604,$A17,Movimientos!$A$5:$A$604,"<"&DATE($B$3,1,1))) | C17: =IF($A17="","",SUMIFS(Movimientos!$I$5:$I$604,Movimientos!$C$5:$C$604,$A17,Movimientos!$J$5:$J$604,$B$3,Movimientos!$I$5:$I$604,1)) | D17: =IF($A17="","",COUNTIFS(Movimientos!$C$5:$C$604,$A17,Movimientos!$J$5:$J$604,$B$3,Movimientos!$D$5:$D$604,"Baja")) | E17: =IF($A17="","",COUNTIFS(Movimientos!$C$5:$C$604,$A17,Movimientos!$J$5:$J$604,$B$3,Movimientos!$D$5:$D$604,"Traslado saliente")) | F17: =IF($A17="","",B17+C17-D17-E17) | G17: =IF($A17="","",SUMIFS(Movimientos!$I$5:$I$604,Movimientos!$C$5:$C$604,$A17)) | H17: =IF($A17="","",IF(F17=SUMIFS(Movimientos!$I$5:$I$604,Movimientos!$C$5:$C$604,$A17,Movimientos!$A$5:$A$604,"<"&DATE($B$3+1,1,1)),"Coincide","Revisa los movimientos"))
B18: =IF($A18="","",SUMIFS(Movimientos!$I$5:$I$604,Movimientos!$C$5:$C$604,$A18,Movimientos!$A$5:$A$604,"<"&DATE($B$3,1,1))) | C18: =IF($A18="","",SUMIFS(Movimientos!$I$5:$I$604,Movimientos!$C$5:$C$604,$A18,Movimientos!$J$5:$J$604,$B$3,Movimientos!$I$5:$I$604,1)) | D18: =IF($A18="","",COUNTIFS(Movimientos!$C$5:$C$604,$A18,Movimientos!$J$5:$J$604,$B$3,Movimientos!$D$5:$D$604,"Baja")) | E18: =IF($A18="","",COUNTIFS(Movimientos!$C$5:$C$604,$A18,Movimientos!$J$5:$J$604,$B$3,Movimientos!$D$5:$D$604,"Traslado saliente")) | F18: =IF($A18="","",B18+C18-D18-E18) | G18: =IF($A18="","",SUMIFS(Movimientos!$I$5:$I$604,Movimientos!$C$5:$C$604,$A18)) | H18: =IF($A18="","",IF(F18=SUMIFS(Movimientos!$I$5:$I$604,Movimientos!$C$5:$C$604,$A18,Movimientos!$A$5:$A$604,"<"&DATE($B$3+1,1,1)),"Coincide","Revisa los movimientos"))
B19: =IF($A19="","",SUMIFS(Movimientos!$I$5:$I$604,Movimientos!$C$5:$C$604,$A19,Movimientos!$A$5:$A$604,"<"&DATE($B$3,1,1))) | C19: =IF($A19="","",SUMIFS(Movimientos!$I$5:$I$604,Movimientos!$C$5:$C$604,$A19,Movimientos!$J$5:$J$604,$B$3,Movimientos!$I$5:$I$604,1)) | D19: =IF($A19="","",COUNTIFS(Movimientos!$C$5:$C$604,$A19,Movimientos!$J$5:$J$604,$B$3,Movimientos!$D$5:$D$604,"Baja")) | E19: =IF($A19="","",COUNTIFS(Movimientos!$C$5:$C$604,$A19,Movimientos!$J$5:$J$604,$B$3,Movimientos!$D$5:$D$604,"Traslado saliente")) | F19: =IF($A19="","",B19+C19-D19-E19) | G19: =IF($A19="","",SUMIFS(Movimientos!$I$5:$I$604,Movimientos!$C$5:$C$604,$A19)) | H19: =IF($A19="","",IF(F19=SUMIFS(Movimientos!$I$5:$I$604,Movimientos!$C$5:$C$604,$A19,Movimientos!$A$5:$A$604,"<"&DATE($B$3+1,1,1)),"Coincide","Revisa los movimientos"))
B20: =IF($A20="","",SUMIFS(Movimientos!$I$5:$I$604,Movimientos!$C$5:$C$604,$A20,Movimientos!$A$5:$A$604,"<"&DATE($B$3,1,1))) | C20: =IF($A20="","",SUMIFS(Movimientos!$I$5:$I$604,Movimientos!$C$5:$C$604,$A20,Movimientos!$J$5:$J$604,$B$3,Movimientos!$I$5:$I$604,1)) | D20: =IF($A20="","",COUNTIFS(Movimientos!$C$5:$C$604,$A20,Movimientos!$J$5:$J$604,$B$3,Movimientos!$D$5:$D$604,"Baja")) | E20: =IF($A20="","",COUNTIFS(Movimientos!$C$5:$C$604,$A20,Movimientos!$J$5:$J$604,$B$3,Movimientos!$D$5:$D$604,"Traslado saliente")) | F20: =IF($A20="","",B20+C20-D20-E20) | G20: =IF($A20="","",SUMIFS(Movimientos!$I$5:$I$604,Movimientos!$C$5:$C$604,$A20)) | H20: =IF($A20="","",IF(F20=SUMIFS(Movimientos!$I$5:$I$604,Movimientos!$C$5:$C$604,$A20,Movimientos!$A$5:$A$604,"<"&DATE($B$3+1,1,1)),"Coincide","Revisa los movimientos"))
... B35: =IF($A35="","",SUMIFS(Movimientos!$I$5:$I$604,Movimientos!$C$5:$C$604,$A35,Movimientos!$A$5:$A$604,"<"&DATE($B$3,1,1))) | C35: =IF($A35="","",SUMIFS(Movimientos!$I$5:$I$604,Movimientos!$C$5:$C$604,$A35,Movimientos!$J$5:$J$604,$B$3,Movimientos!$I$5:$I$604,1)) | D35: =IF($A35="","",COUNTIFS(Movimientos!$C$5:$C$604,$A35,Movimientos!$J$5:$J$604,$B$3,Movimientos!$D$5:$D$604,"Baja")) | E35: =IF($A35="","",COUNTIFS(Movimientos!$C$5:$C$604,$A35,Movimientos!$J$5:$J$604,$B$3,Movimientos!$D$5:$D$604,"Traslado saliente")) | F35: =IF($A35="","",B35+C35-D35-E35) | G35: =IF($A35="","",SUMIFS(Movimientos!$I$5:$I$604,Movimientos!$C$5:$C$604,$A35)) | H35: =IF($A35="","",IF(F35=SUMIFS(Movimientos!$I$5:$I$604,Movimientos!$C$5:$C$604,$A35,Movimientos!$A$5:$A$604,"<"&DATE($B$3+1,1,1)),"Coincide","Revisa los movimientos"))
A36: Total | B36: =SUM(B6:B35) | C36: =SUM(C6:C35) | D36: =SUM(D6:D35) | E36: =SUM(E6:E35) | F36: =SUM(F6:F35) | G36: =SUM(G6:G35)
